flake8_comments/__init__.py
flake8_comments/_checker.py
flake8_comments/_core.py
flake8_comments/_stop_words.py
flake8_comments-0.1.2.dist-info/entry_points.txt
flake8_comments-0.1.2.dist-info/LICENSE
flake8_comments-0.1.2.dist-info/WHEEL
flake8_comments-0.1.2.dist-info/METADATA
flake8_comments-0.1.2.dist-info/RECORD
