Metadata-Version: 1.1
Name: flake8-comments
Version: 0.1.2
Summary: Find redundant comments in Python code
Home-page: https://github.com/orsinium-labs/flake8-comments
Author: Gram
Author-email: gram@orsinium.dev
